LICENSE
MANIFEST.in
README
README.rst
setup.py
src/.vscode/settings.json
src/facond/.eslintrc.js
src/facond/__init__.py
src/facond/actions.js
src/facond/actions.py
src/facond/actions.test.js
src/facond/conditions.js
src/facond/conditions.py
src/facond/conditions.test.js
src/facond/forms.js
src/facond/forms.py
src/facond/forms.test.js
src/facond/index.js
src/facond/index.test.js
src/facond/js.py
src/facond/js_test.py
src/facond/package-lock.json
src/facond/package.json
src/facond/shortcuts.py
src/facond/webpack.config.js
src/facond.egg-info/PKG-INFO
src/facond.egg-info/SOURCES.txt
src/facond.egg-info/dependency_links.txt
src/facond.egg-info/entry_points.txt
src/facond.egg-info/not-zip-safe
src/facond.egg-info/requires.txt
src/facond.egg-info/top_level.txt
src/facond/static/facond.js
src/facond_examples/__init__.py
src/facond_examples/main.js
src/facond_examples/manage.py
src/facond_examples/package-lock.json
src/facond_examples/package.json
src/facond_examples/settings.py
src/facond_examples/urls.py
src/facond_examples/wsgi.py
src/facond_examples/remove_choices/__init__.py
src/facond_examples/remove_choices/forms.py
src/facond_examples/remove_choices/models.py
src/facond_examples/remove_choices/test_integration.py
src/facond_examples/remove_choices_multiple/__init__.py
src/facond_examples/remove_choices_multiple/forms.py
src/facond_examples/remove_choices_multiple/models.py
src/facond_examples/remove_choices_multiple/test_integration.py
src/facond_examples/remove_fields/__init__.py
src/facond_examples/remove_fields/forms.py
src/facond_examples/remove_fields/test_integration.py
src/facond_examples/templates/base.html
src/facond_examples/templates/form.html
src/facond_examples/templates/formset.html